PythonOpencvJisuanjiShijueChuyiFix1/README.md
PythonOpencvJisuanjiShijueChuyiFix1/__init__.py
PythonOpencvJisuanjiShijueChuyiFix1/__main__.py
PythonOpencvJisuanjiShijueChuyiFix1/file.epub
PythonOpencvJisuanjiShijueChuyiFix1/index.html
PythonOpencvJisuanjiShijueChuyiFix1/css/__init__.py
PythonOpencvJisuanjiShijueChuyiFix1/css/annotations.css
PythonOpencvJisuanjiShijueChuyiFix1/css/main.css
PythonOpencvJisuanjiShijueChuyiFix1/css/normalize.css
PythonOpencvJisuanjiShijueChuyiFix1/css/popup.css
PythonOpencvJisuanjiShijueChuyiFix1/font/__init__.py
PythonOpencvJisuanjiShijueChuyiFix1/font/fontello.eot
PythonOpencvJisuanjiShijueChuyiFix1/font/fontello.svg
PythonOpencvJisuanjiShijueChuyiFix1/font/fontello.ttf
PythonOpencvJisuanjiShijueChuyiFix1/font/fontello.woff
PythonOpencvJisuanjiShijueChuyiFix1/img/__init__.py
PythonOpencvJisuanjiShijueChuyiFix1/img/annotator-glyph-sprite.png
PythonOpencvJisuanjiShijueChuyiFix1/img/annotator-icon-sprite.png
PythonOpencvJisuanjiShijueChuyiFix1/img/apple-touch-icon.png
PythonOpencvJisuanjiShijueChuyiFix1/img/cancelfullscreen.png
PythonOpencvJisuanjiShijueChuyiFix1/img/close.png
PythonOpencvJisuanjiShijueChuyiFix1/img/fullscreen.png
PythonOpencvJisuanjiShijueChuyiFix1/img/loader.gif
PythonOpencvJisuanjiShijueChuyiFix1/img/menu-icon.png
PythonOpencvJisuanjiShijueChuyiFix1/img/save.png
PythonOpencvJisuanjiShijueChuyiFix1/img/saved.png
PythonOpencvJisuanjiShijueChuyiFix1/img/settings-s.png
PythonOpencvJisuanjiShijueChuyiFix1/img/settings.png
PythonOpencvJisuanjiShijueChuyiFix1/img/star.png
PythonOpencvJisuanjiShijueChuyiFix1/js/__init__.py
PythonOpencvJisuanjiShijueChuyiFix1/js/epub.js
PythonOpencvJisuanjiShijueChuyiFix1/js/epub.min.js
PythonOpencvJisuanjiShijueChuyiFix1/js/epub.min.map
PythonOpencvJisuanjiShijueChuyiFix1/js/hooks.min.js
PythonOpencvJisuanjiShijueChuyiFix1/js/hooks.min.map
PythonOpencvJisuanjiShijueChuyiFix1/js/reader.js
PythonOpencvJisuanjiShijueChuyiFix1/js/reader.js.map
PythonOpencvJisuanjiShijueChuyiFix1/js/reader.min.js
python_opencv_jisuanji_shijue_chuyi_fix1-2025.3.25.0.dist-info/METADATA
python_opencv_jisuanji_shijue_chuyi_fix1-2025.3.25.0.dist-info/WHEEL
python_opencv_jisuanji_shijue_chuyi_fix1-2025.3.25.0.dist-info/entry_points.txt
python_opencv_jisuanji_shijue_chuyi_fix1-2025.3.25.0.dist-info/top_level.txt
python_opencv_jisuanji_shijue_chuyi_fix1-2025.3.25.0.dist-info/RECORD
